spotysend
